{
  "id": "d507230c03c17440",
  "title": "Message Contract Governance and Testing",
  "category": "catalog",
  "canonicalPath": "knowledge/catalog/message-contract/governance-and-testing.md",
  "sourceHash": "ab68eec853752f1136861b65132b966f18a78bfbef673f2420a8ae0ec4f554c6",
  "headings": [
    {
      "level": 1,
      "text": "Message Contract Governance and Testing"
    },
    {
      "level": 2,
      "text": "Purpose"
    },
    {
      "level": 2,
      "text": "Source"
    },
    {
      "level": 2,
      "text": "Governance"
    },
    {
      "level": 2,
      "text": "Testing"
    }
  ],
  "bodyMarkdown": "# Message Contract Governance and Testing\r\n\r\n## Purpose\r\nThis split document isolates message contract security, audit, validation, testing, edge cases, and consistency checks from the parent Message Contract Catalog.\r\n\r\n## Source\r\n- Parent specification: [Message Contract Catalog](../message-contract-catalog.md)\r\n\r\n## Governance\r\nGovernance covers ownership, schema validation, permission mapping, field masking, audit metadata, contract lifecycle, compatibility review, and release controls.\r\n\r\n## Testing\r\nTesting covers producer contracts, consumer contracts, schema validation, replay, retry, dead letter, compatibility, permission masking, and edge cases.\r\n\r\n",
  "references": []
}